LICENSE.txt
README.rst
setup.cfg
setup.py
tgthon/FasterTg.py
tgthon/__init__.py
tgthon/mystarts.py
tgthon/pyfunc.py
tgthon/pyutils.py
tgthon/telefunc.py
tgthon/teleutils.py
tgthon/uploader.py
tgthon.egg-info/PKG-INFO
tgthon.egg-info/SOURCES.txt
tgthon.egg-info/dependency_links.txt
tgthon.egg-info/requires.txt
tgthon.egg-info/top_level.txt